soffosai/__init__.py
soffosai/client/__init__.py
soffosai/client/ai_response.py
soffosai/common/__init__.py
soffosai/common/constants.py
soffosai/common/service_io_map.py
soffosai/common/serviceio_fields/__init__.py
soffosai/common/serviceio_fields/answer_scoring.py
soffosai/common/serviceio_fields/assessment_generator.py
soffosai/common/serviceio_fields/audio_converter.py
soffosai/common/serviceio_fields/chat.py
soffosai/common/serviceio_fields/chat_bot.py
soffosai/common/serviceio_fields/chat_bot_create.py
soffosai/common/serviceio_fields/chat_bot_delete_user_sessions.py
soffosai/common/serviceio_fields/chat_bot_get_user_sessions.py
soffosai/common/serviceio_fields/chat_bots_delete.py
soffosai/common/serviceio_fields/chat_bots_get.py
soffosai/common/serviceio_fields/discuss_count.py
soffosai/common/serviceio_fields/discuss_create.py
soffosai/common/serviceio_fields/discuss_delete.py
soffosai/common/serviceio_fields/discuss_query.py
soffosai/common/serviceio_fields/documents_count.py
soffosai/common/serviceio_fields/documents_delete.py
soffosai/common/serviceio_fields/documents_ingest.py
soffosai/common/serviceio_fields/documents_search.py
soffosai/common/serviceio_fields/email_analysis.py
soffosai/common/serviceio_fields/emotion_detection.py
soffosai/common/serviceio_fields/file_converter.py
soffosai/common/serviceio_fields/image_analysis.py
soffosai/common/serviceio_fields/image_generation.py
soffosai/common/serviceio_fields/language_detection.py
soffosai/common/serviceio_fields/logical_error_detection.py
soffosai/common/serviceio_fields/microlesson.py
soffosai/common/serviceio_fields/multiple_choice_qn_a_generator.py
soffosai/common/serviceio_fields/named_entity_recognition.py
soffosai/common/serviceio_fields/natural_s_q_l_generation.py
soffosai/common/serviceio_fields/paraphrase.py
soffosai/common/serviceio_fields/profanity.py
soffosai/common/serviceio_fields/qna_generation.py
soffosai/common/serviceio_fields/question_answering.py
soffosai-0.2.4.dist-info/LICENSE
soffosai-0.2.4.dist-info/METADATA
soffosai-0.2.4.dist-info/WHEEL
soffosai-0.2.4.dist-info/top_level.txt
soffosai-0.2.4.dist-info/RECORD
