Metadata-Version: 2.1
Name: soffosai
Version: 0.2.4
Summary: Python SDK for Soffos AI
Author: Soffosai
Author-email: "Soffos.ai" <Soffos@Soffos.ai>, Franco Such <franco.such@Soffos.ai>
Project-URL: Homepage, https://github.com/Soffos-Inc/soffos_ai
Project-URL: Bug Tracker, https://github.com/Soffos-Inc/soffos_ai/issues
Classifier: Programming Language :: Python :: 3
Classifier: License :: OSI Approved :: MIT License
Classifier: Operating System :: OS Independent
Requires-Python: >=3.7
License-File: LICENSE
Requires-Dist: requests
